{
    "education":[
        {
            "title": "Aug 2022 - May 2024",
            "cardTitle": "M.S., Management Information Systems",
            "cardSubtitle":"Texas A&M University, College Station",
            "cardDetailedText": "GPA - 3.8",
            "icon" : {
                "src": "images/education/tamu.png"
            }
        },
        {
            "title": "Aug 2015 - May 2019",
            "cardTitle": "B.Tech, Computer Science",
            "cardSubtitle":"A.P.J. Abdul Kalam Technological University",
            "cardDetailedText": "GPA - 3.6",
            "icon" : {
                "src": "images/education/ktu.png"
            }
        }
    ]
}
